maintainers_and_authors/__about__.py
maintainers_and_authors/__init__.py
maintainers_and_authors/__main__.py
maintainers_and_authors/api.py
maintainers_and_authors/cli.py
maintainers_and_authors/core.py
maintainers_and_authors-0.0.3.dist-info/METADATA
maintainers_and_authors-0.0.3.dist-info/WHEEL
maintainers_and_authors-0.0.3.dist-info/entry_points.txt
maintainers_and_authors-0.0.3.dist-info/licenses/LICENSE.txt
maintainers_and_authors-0.0.3.dist-info/RECORD
