Metadata-Version: 2.4
Name: maintainers-and-authors
Version: 0.0.3
Summary: Gets the author and maintainer emails for projects passed to stdin via wheelodex.
Project-URL: Issues, https://github.com/JamesParrott/maintainers-and-authors/issues
Project-URL: Source, https://github.com/JamesParrott/maintainers-and-authors
Author-email: James Parrott <james.parrott@proton.me>
License-Expression: MIT
License-File: LICENSE.txt
Classifier: Development Status :: 4 - Beta
Classifier: Programming Language :: Python
Classifier: Programming Language :: Python :: 3.9
Classifier: Programming Language :: Python :: Implementation :: CPython
Requires-Python: >=3.9
Requires-Dist: requests
